xwire/scientific/__init__.py
xwire/scientific/_private/__init__.py
xwire/scientific/_private/data/__init__.py
xwire/scientific/_private/data/_data_utils.py
xwire/scientific/_private/math/__init__.py
xwire/scientific/_private/math/_math.py
xwire/scientific/_private/model/__init__.py
xwire/scientific/_private/model/_model.py
xwire/scientific/public/__init__.py
xwire/scientific/public/data.py
xwire/scientific/public/math.py
xwire/scientific/public/model.py
xwire.scientific-0.1.3.dist-info/WHEEL
xwire.scientific-0.1.3.dist-info/METADATA
xwire.scientific-0.1.3.dist-info/RECORD
