Metadata-Version: 2.1
Name: xwire.scientific
Version: 0.1.3
Summary: 
Author: tylerlaberge
Author-email: tylerlaberge@protonmail.com
Requires-Python: >=3.8,<4.0
Classifier: Programming Language :: Python :: 3
Classifier: Programming Language :: Python :: 3.8
Classifier: Programming Language :: Python :: 3.9
Requires-Dist: joblib (>=1.0.1,<2.0.0)
Requires-Dist: pandas (>=1.2.3,<2.0.0)
Requires-Dist: scikit-learn (>=0.24.1,<0.25.0)
